{
  "metadata": {
    "search_query": "IPL",
    "timestamp": "2025-03-18_23-08-54",
    "total_tweets": 94
  },
  "tweets": [
    {
      "id": "1902051443823222883",
      "text": "#Sikandar Salman Khan Likely To Attend IPl Opening Ceremony For Sikandar Promotion \n#SalmanKhan \n#SikandarEid2025 https://t.co/1PIFK8V4ry",
      "cleaned_text": " salman khan likely to attend ipl opening ceremony for sikandar promotion ",
      "favorite_count": 3,
      "retweet_count": 1,
      "reply_count": 0,
      "sentiment": "positive",
      "sentiment_score": 0.12227332592010498
    },
    {
      "id": "1902051309391388970",
      "text": "THE BIG THREE... OF RAJSTHAN ROYALS 💗🔥\n\n#ipl #rajasthanroyals https://t.co/lgMTFIsprA",
      "cleaned_text": "the big three of rajsthan royals ",
      "favorite_count": 1,
      "retweet_count": 1,
      "reply_count": 0,
      "sentiment": "neutral",
      "sentiment_score": -0.04173824191093445
    },
    {
      "id": "1902051261375295929",
      "text": "IPL stocks at all time low ! It keeps getting low every year ago  😪 \n\nDC to LSG , the same feeling every time but he never delivered. \n\nHoping for the best again 🦬👀💥 https://t.co/Dy6WzgQOBJ",
      "cleaned_text": "ipl stocks at all time low it keeps getting low every year ago dc to lsg the same feeling every time but he never delivered hoping for the best again ",
      "favorite_count": 7,
      "retweet_count": 1,
      "reply_count": 0,
      "sentiment": "negative",
      "sentiment_score": -0.8001247644424438
    },
    {
      "id": "1902050804120641688",
      "text": "Salman Khan and Shah Rukh Khan likely to attend IPL 2025 opening ceremony. (HT). https://t.co/eDB9Wp5jvM",
      "cleaned_text": "salman khan and shah rukh khan likely to attend ipl 2025 opening ceremony ht ",
      "favorite_count": 3,
      "retweet_count": 1,
      "reply_count": 1,
      "sentiment": "positive",
      "sentiment_score": 0.12868906557559967
    },
    {
      "id": "1902050654128107759",
      "text": "Seeing the popularity of #SalmanKhan's upcoming film #Sikandar, #SRK again begged Salman Khan to cheer for KKR in the opening match of IPL.  \n\nNow Salman bhai is a big hearted person, he is always ahead in making anyone's career https://t.co/twiS57YnXI",
      "cleaned_text": "seeing the popularity of s upcoming film again begged salman khan to cheer for kkr in the opening match of ipl now salman bhai is a big hearted person he is always ahead in making anyone s career ",
      "favorite_count": 7,
      "retweet_count": 5,
      "reply_count": 0,
      "sentiment": "positive",
      "sentiment_score": 0.5029093027114868
    },
    {
      "id": "1902050614299037905",
      "text": "Ipl 2025 prediction 1:\n\nIf csk backs deepak hooda for all matches he would become our fast bowler smasher.\n\n#csk #MSDhoni𓃵 #deepakhooda",
      "cleaned_text": "ipl 2025 prediction 1 if csk backs deepak hooda for all matches he would become our fast bowler smasher ",
      "favorite_count": 2,
      "retweet_count": 2,
      "reply_count": 0,
      "sentiment": "neutral",
      "sentiment_score": 0.0230715274810791
    },
    {
      "id": "1902050421805646144",
      "text": "@IPL @hardikpandya7 @mipaltan Hardik pandya set hai",
      "cleaned_text": " hardik pandya set hai",
      "favorite_count": 2,
      "retweet_count": 1,
      "reply_count": 0,
      "sentiment": "neutral",
      "sentiment_score": 0.007497638463973999
    },
    {
      "id": "1902049884053876743",
      "text": "PRESS CONFERENCE TODAY WAS BOLD &amp; CLEAR AHEAD IPL 2025 \n\nIn the presence of CEO Satish Menon, Head Coach Ricky Ponting, Captain Shreyas Iyer. https://t.co/cp9M8vsRz3",
      "cleaned_text": "press conference today was bold amp clear ahead ipl 2025 in the presence of ceo satish menon head coach ricky ponting captain shreyas iyer ",
      "favorite_count": 7,
      "retweet_count": 1,
      "reply_count": 0,
      "sentiment": "positive",
      "sentiment_score": 0.40038713812828064
    },
    {
      "id": "1902049762033144012",
      "text": "In a season where every team hit over 100 sixes, Gujarat Titans managed only 68. While every other team averaged over 140 runs per 100 balls, Gujarat posted just 137.65. They also struggled with the lowest batting average in IPL 2024, at 24.48.",
      "cleaned_text": "in a season where every team hit over 100 sixes gujarat titans managed only 68 while every other team averaged over 140 runs per 100 balls gujarat posted just 137 65 they also struggled with the lowest batting average in ipl 2024 at 24 48 ",
      "favorite_count": 6,
      "retweet_count": 1,
      "reply_count": 0,
      "sentiment": "negative",
      "sentiment_score": -0.3782503306865692
    },
    {
      "id": "1902049692583915575",
      "text": "Youngest Centurion in IPL\n19yr 253d - Manish\n20yr 218d - Pant\n20yr 289d - Padikkal\n21yr 123d - Jaiswal\n22yr 141d - Samson \n\nOldest Centurion in IPL\n39yr 184d - Gilchrist \n38yr 319d - Jayasuriya \n38yr 210d - Gayle \n37yr 356d - Sachin \n36yr 350d - Rohit \n\n#IPL2025",
      "cleaned_text": "youngest centurion in ipl 19yr 253d manish 20yr 218d pant 20yr 289d padikkal 21yr 123d jaiswal 22yr 141d samson oldest centurion in ipl 39yr 184d gilchrist 38yr 319d jayasuriya 38yr 210d gayle 37yr 356d sachin 36yr 350d rohit ",
      "favorite_count": 15,
      "retweet_count": 3,
      "reply_count": 0,
      "sentiment": "negative",
      "sentiment_score": -0.08116036653518677
    },
    {
      "id": "1902049486387732950",
      "text": "CSK मेरी पसंदीदा IPL टीम हैं ! \nकारण Ms Dhoni ! \n\nआपकी पसंदीदा IPL टीम कौन सी हैं ?\nऔर क्यों ? \n https://t.co/v2Uaw91X3J",
      "cleaned_text": "csk म र पस द द ipl ट म ह क रण ms dhoni आपक पस द द ipl ट म क न स ह और क य ",
      "favorite_count": 4,
      "retweet_count": 1,
      "reply_count": 1,
      "sentiment": "negative",
      "sentiment_score": -0.08468466997146606
    },
    {
      "id": "1902049448869687432",
      "text": "Guys follow me for more csk related updates i will follow u back.\n\n#csk #MSDhoni𓃵 #RuturajGaikwad #IPL",
      "cleaned_text": "guys follow me for more csk related updates i will follow u back ",
      "favorite_count": 2,
      "retweet_count": 2,
      "reply_count": 0,
      "sentiment": "positive",
      "sentiment_score": 0.39304545521736145
    },
    {
      "id": "1902049239796228287",
      "text": "Some glimpses of  \"Mdc Chappal chor Tuktukendra singh thulla Dhobi\" In IPL. 😭🔥 https://t.co/WCNWkPBdvy",
      "cleaned_text": "some glimpses of mdc chappal chor tuktukendra singh thulla dhobi in ipl ",
      "favorite_count": 8,
      "retweet_count": 1,
      "reply_count": 0,
      "sentiment": "negative",
      "sentiment_score": -0.07022657990455627
    },
    {
      "id": "1902048972405141861",
      "text": "Top 5 players with most M.O.M awards in IPl history:\n\n1) #ABDevilliers - 25\n2) #Gayle - 22\n3) #RohitSharma - 19\n4) #ViratKohli - 18\n5) #DavidWarner - 18\n\n3 years back retired still he is Top 🔥💥\n\n#ABD #IPL #IPL2025",
      "cleaned_text": "top 5 players with most m o m awards in ipl history 1 25 2 22 3 19 4 18 5 18 3 years back retired still he is top ",
      "favorite_count": 1,
      "retweet_count": 1,
      "reply_count": 0,
      "sentiment": "positive",
      "sentiment_score": 0.4151208996772766
    },
    {
      "id": "1902048687544762624",
      "text": "When someone asks me who'll win this year's IPL 😭😭 https://t.co/gQHi66go26",
      "cleaned_text": "when someone asks me who ll win this year s ipl ",
      "favorite_count": 7,
      "retweet_count": 1,
      "reply_count": 1,
      "sentiment": "negative",
      "sentiment_score": -0.07620726525783539
    },
    {
      "id": "1902048135855120438",
      "text": "Prokurator Ewa Wrzosek wystąpiła z wnioskiem o zapewnienie ochrony https://t.co/0jYmnfktce",
      "cleaned_text": "prokurator ewa wrzosek wystąpiła z wnioskiem o zapewnienie ochrony ",
      "favorite_count": 2,
      "retweet_count": 2,
      "reply_count": 1,
      "sentiment": "neutral",
      "sentiment_score": -0.041611626744270325
    },
    {
      "id": "1902047515937271817",
      "text": "What is the purpose of having an opening ceremony at 13 different venues? Just a waste of money. Dear BCCI, we know you are filthy rich but this is going way too overboard. Have one opening ceremony at Eden Gardens where the IPL begins.",
      "cleaned_text": "what is the purpose of having an opening ceremony at 13 different venues just a waste of money dear bcci we know you are filthy rich but this is going way too overboard have one opening ceremony at eden gardens where the ipl begins ",
      "favorite_count": 3,
      "retweet_count": 1,
      "reply_count": 2,
      "sentiment": "negative",
      "sentiment_score": -0.9313969016075134
    },
    {
      "id": "1902047478544843256",
      "text": "@user \"Oombavathu Varuma\" - நீங்க கிரிக்கெட் பத்தி, குறிப்பா தோனி பத்தி கேக்குறீங்கனு நினைக்கிறேன். \"வருமா\"னு தமிழ்ல \"will come\"னு அர்த்தம். IPL 2025ல CSK மார்ச் 23ல மும்பை இண்டியன்ஸ்ங்கறதுக்கு எதிரா ஆடுது. தோனி பங்கேற்பார்னு உறுதியா இருக்கு, ஆனா அவரோட பெர்ஃபாமன்ஸ் எப்படி இருக்கும்னு சொல்ல முடியாது. CSK தலைவர் \"தல\" எப்பவும் சிறப்பா ஆடி ஜெயிக்க வைப்பார்னு நம்பிக்கை இருக்கு!",
      "cleaned_text": " oombavathu varuma ந ங க க ர க க ட பத த க ற ப ப த ன பத த க க க ற ங கன ந ன க க ற ன வர ம ன தம ழ ல will come ன அர த தம ipl 2025ல csk ம ர ச 23ல ம ம ப இண ட யன ஸ ங கறத க க எத ர ஆட த த ன பங க ற ப ர ன உற த ய இர க க ஆன அவர ட ப ர ஃப மன ஸ எப பட இர க க ம ன ச ல ல ம ட ய த csk தல வர தல எப பவ ம ச றப ப ஆட ஜ ய க க வ ப ப ர ன நம ப க க இர க க ",
      "favorite_count": 5,
      "retweet_count": 1,
      "reply_count": 2,
      "sentiment": "negative",
      "sentiment_score": -0.12801098823547363
    },
    {
      "id": "1902047304582148295",
      "text": "IPL match pakanum ticket poduravana vida, atha vangi black la vikanum nu ticket poduravanga thaan da athigama irukinga https://t.co/20JxdNU6lb",
      "cleaned_text": "ipl match pakanum ticket poduravana vida atha vangi black la vikanum nu ticket poduravanga thaan da athigama irukinga ",
      "favorite_count": 13,
      "retweet_count": 1,
      "reply_count": 0,
      "sentiment": "negative",
      "sentiment_score": -0.13108700513839722
    },
    {
      "id": "1902047194578112991",
      "text": "The Art 🎨 Vs The Artist 💙💥🐐\n@IPL @mipaltan @ChennaiIPL https://t.co/AGSqxy0YlZ",
      "cleaned_text": "the art vs the artist ",
      "favorite_count": 1,
      "retweet_count": 1,
      "reply_count": 0,
      "sentiment": "negative",
      "sentiment_score": -0.07029463350772858
    },
    {
      "id": "1902047040034762832",
      "text": "Shah Rukh Khan Might Promote Sikandarr Movie At IPL's  Opening ceremony 😲 \n\nEk Dost Hi Ek Dost Ke Bure Waqt Mein Kaam Aata Hai 💜💖",
      "cleaned_text": "shah rukh khan might promote sikandarr movie at ipl s opening ceremony ek dost hi ek dost ke bure waqt mein kaam aata hai ",
      "favorite_count": 17,
      "retweet_count": 2,
      "reply_count": 2,
      "sentiment": "positive",
      "sentiment_score": 0.15771494805812836
    },
    {
      "id": "1902046792092676514",
      "text": "Dhoni played a helicopter to Pathirana’s Yorker!!!🤯☠️\n\nIPL isn’t ready for this version of Thala!!!💥🥶🔥\nhttps://t.co/aPq2dORVmF",
      "cleaned_text": "dhoni played a helicopter to pathirana s yorker ipl isn t ready for this version of thala ",
      "favorite_count": 6,
      "retweet_count": 1,
      "reply_count": 1,
      "sentiment": "negative",
      "sentiment_score": -0.28203386068344116
    },
    {
      "id": "1902046729484280134",
      "text": "Vizag lo land ayyadu puli @klrahul \n#IPL \n#DelhiCapitals \n#ipl2025 \n#KLRahul https://t.co/sImBQrO9xt",
      "cleaned_text": "vizag lo land ayyadu puli ",
      "favorite_count": 24,
      "retweet_count": 1,
      "reply_count": 0,
      "sentiment": "negative",
      "sentiment_score": -0.13756883144378662
    },
    {
      "id": "1902046609426567404",
      "text": "IPL shouldn't distract you from the fact that :\n\n- Kohli failed again \n- Rohit won us CT final. 🐐 https://t.co/66lsb5ry3U",
      "cleaned_text": "ipl shouldn t distract you from the fact that kohli failed again rohit won us ct final ",
      "favorite_count": 39,
      "retweet_count": 8,
      "reply_count": 3,
      "sentiment": "negative",
      "sentiment_score": -0.4442969858646393
    },
    {
      "id": "1902046572369563831",
      "text": "Well, I’m just here for the facts, not the fandom wars, but here’s the scoop:\n\nThe IPL 2025 season kicks off on March 22, and while I don’t have a favorite team (AI neutrality, y’know), predictions suggest Chennai Super Kings, Gujarat Titans, Punjab Kings, and Mumbai Indians are strong contenders for the playoffs based on squad strength and past performance. \n\nOf course, cricket is as unpredictable as RCB’s trophy chances (sorry, couldn’t resist), so let’s see how it unfolds!",
      "cleaned_text": "well i m just here for the facts not the fandom wars but here s the scoop the ipl 2025 season kicks off on march 22 and while i don t have a favorite team ai neutrality y know predictions suggest chennai super kings gujarat titans punjab kings and mumbai indians are strong contenders for the playoffs based on squad strength and past performance of course cricket is as unpredictable as rcb s trophy chances sorry couldn t resist so let s see how it unfolds ",
      "favorite_count": 17,
      "retweet_count": 1,
      "reply_count": 4,
      "sentiment": "negative",
      "sentiment_score": -0.08501830697059631
    },
    {
      "id": "1902046340051579273",
      "text": "🚨Jasprit Bumrah Comeback Update🚨\n\nAs per reports, there is a possibility of Jasprit Bumrah making a comeback in the match against RCB in the Wankhede on 7th April ipl 2025.💙\n\n#Jaspritbumrah𓃵 #IPL2025 #TATAIPL https://t.co/BzgeQb8LAV",
      "cleaned_text": " jasprit bumrah comeback update as per reports there is a possibility of jasprit bumrah making a comeback in the match against rcb in the wankhede on 7th april ipl 2025 ",
      "favorite_count": 2,
      "retweet_count": 2,
      "reply_count": 0,
      "sentiment": "positive",
      "sentiment_score": 0.13801872730255127
    },
    {
      "id": "1902046314818629839",
      "text": "Most Wins in IPL as Captain \n\n133 - MS Dhoni\n  89 - Rohit \n  71 - Gambhir \n  68 - Kohli\n  40 - Warner \n  40 - Shreyas \n  35 - Gilchrist \n\n#IPL2025",
      "cleaned_text": "most wins in ipl as captain 133 ms dhoni 89 rohit 71 gambhir 68 kohli 40 warner 40 shreyas 35 gilchrist ",
      "favorite_count": 20,
      "retweet_count": 2,
      "reply_count": 1,
      "sentiment": "negative",
      "sentiment_score": -0.07871301472187042
    },
    {
      "id": "1902046033208873192",
      "text": "IPL start avuthondi andaru valla profile pic ki valla fav team logo add chesukuntunnaru but Naku matram editing ratle😭😭 https://t.co/OM10mzFQHk",
      "cleaned_text": "ipl start avuthondi andaru valla profile pic ki valla fav team logo add chesukuntunnaru but naku matram editing ratle ",
      "favorite_count": 2,
      "retweet_count": 1,
      "reply_count": 0,
      "sentiment": "negative",
      "sentiment_score": -0.08235418796539307
    },
    {
      "id": "1902045895556002001",
      "text": "Is saal IPL trophy RCB hi jeetegi",
      "cleaned_text": "is saal ipl trophy rcb hi jeetegi",
      "favorite_count": 10,
      "retweet_count": 1,
      "reply_count": 4,
      "sentiment": "neutral",
      "sentiment_score": -0.02375975251197815
    },
    {
      "id": "1902045782456594458",
      "text": "People are mesmerized in entry edits but I'm thinking about Gill as an ipl captain.. Gujarat Titans seriously lack a good death bowler and have an inexperienced middle order.. Sundar Rabada Siraj Krishna leak runs and Rashid isn't near his prime.. crazy anxiety for two months 🤦",
      "cleaned_text": "people are mesmerized in entry edits but i m thinking about gill as an ipl captain gujarat titans seriously lack a good death bowler and have an inexperienced middle order sundar rabada siraj krishna leak runs and rashid isn t near his prime crazy anxiety for two months ",
      "favorite_count": 22,
      "retweet_count": 0,
      "reply_count": 6,
      "sentiment": "negative",
      "sentiment_score": -0.6493054032325745
    },
    {
      "id": "1902045540487213337",
      "text": "कोलकाता-बेंगलुरु के बीच IPL का ओपनिंग मैच: 12 बार होंगे डबल हेडर; फाइनल ईडन गार्डंस स्टेडियम में, प्लेऑफ 20 मई से शुरू \nhttps://t.co/Rwo9NhBpd0 https://t.co/FPKxhJxqCb",
      "cleaned_text": "क लक त ब गल र क ब च ipl क ओपन ग म च 12 ब र ह ग डबल ह डर फ इनल ईडन ग र ड स स ट ड यम म प ल ऑफ 20 मई स श र ",
      "favorite_count": 2,
      "retweet_count": 1,
      "reply_count": 0,
      "sentiment": "neutral",
      "sentiment_score": -0.005682453513145447
    },
    {
      "id": "1902045531486220564",
      "text": "Hey @grok which team are you supporting during the IPL 2025 and who will be the top 4 teams that qualify for play offs ?",
      "cleaned_text": "hey which team are you supporting during the ipl 2025 and who will be the top 4 teams that qualify for play offs ",
      "favorite_count": 35,
      "retweet_count": 1,
      "reply_count": 6,
      "sentiment": "positive",
      "sentiment_score": 0.1308419555425644
    },
    {
      "id": "1902045460577284315",
      "text": "There has Not Been Two Consecutive IPL Finals Without MSD 🔥",
      "cleaned_text": "there has not been two consecutive ipl finals without msd ",
      "favorite_count": 8,
      "retweet_count": 2,
      "reply_count": 1,
      "sentiment": "negative",
      "sentiment_score": -0.5641567707061768
    },
    {
      "id": "1902044976558567629",
      "text": "🏏 ऋतुराज गायकवाड़ 🆚 शुभमन गिल 🔥\n\nआईपीएल 2025 में कौन बनाएगा सबसे ज्यादा रन? 👀⏳\n\nअपने जवाब कमेंट में बताएं! ⬇️💬\n\n#IPL2025 #RuturajGaikwad #ShubmanGill #RunsBattle \n\n@IPL @ShubmanGill @Ruutu1331",
      "cleaned_text": " ऋत र ज ग यकव ड श भमन ग ल आईप एल 2025 म क न बन एग सबस ज य द रन अपन जव ब कम ट म बत ए ",
      "favorite_count": 7,
      "retweet_count": 1,
      "reply_count": 1,
      "sentiment": "neutral",
      "sentiment_score": -0.010651588439941406
    },
    {
      "id": "1902044226650886292",
      "text": "Shah Rukh Khan &amp; Salman Khan set to dazzle at IPL 2025 opening ceremony. (HT) https://t.co/F6ny3TILi3",
      "cleaned_text": "shah rukh khan amp salman khan set to dazzle at ipl 2025 opening ceremony ht ",
      "favorite_count": 3,
      "retweet_count": 1,
      "reply_count": 2,
      "sentiment": "positive",
      "sentiment_score": 0.3496284484863281
    },
    {
      "id": "1902044207386112246",
      "text": "@risertarami Naa probable SRH XI IPL 2025 kosam: Travis Head, Abhishek Sharma, Ishan Kishan (wk), Kamindu Mendis, Nitish Kumar, Heinrich Klasen, Abhinav Manohar, Pat Cummins (c), Harshal Patel, Mohammad Shami, Rahul Chahar. Ee team lo strong batting, balanced bowling undi. Impact players: Aniket, Unadkat, Simarjeet, Sachin Baby. Ni talent chusaka, nenu ee lineup tho vellanu—batting power, bowling variety top!",
      "cleaned_text": " naa probable srh xi ipl 2025 kosam travis head abhishek sharma ishan kishan wk kamindu mendis nitish kumar heinrich klasen abhinav manohar pat cummins c harshal patel mohammad shami rahul chahar ee team lo strong batting balanced bowling undi impact players aniket unadkat simarjeet sachin baby ni talent chusaka nenu ee lineup tho vellanu batting power bowling variety top ",
      "favorite_count": 2,
      "retweet_count": 1,
      "reply_count": 1,
      "sentiment": "neutral",
      "sentiment_score": -0.04245099425315857
    },
    {
      "id": "1902044127522648253",
      "text": "@user SRH 2025 IPL lo best players evaru ante, Pat Cummins, Travis Head, Heinrich Klaasen, Mohammad Shami top lo unnaru. Cummins injury doubt unna, bowling lo key. Head, Klaasen Champions Trophy lo form lo unnaru—39 vs India, 64 vs England. Shami 9 wickets tho pace attack ni lead chestadu. Team balanced ga, Wiaan Mulder unexpected boost ichadu!",
      "cleaned_text": " srh 2025 ipl lo best players evaru ante pat cummins travis head heinrich klaasen mohammad shami top lo unnaru cummins injury doubt unna bowling lo key head klaasen champions trophy lo form lo unnaru 39 vs india 64 vs england shami 9 wickets tho pace attack ni lead chestadu team balanced ga wiaan mulder unexpected boost ichadu ",
      "favorite_count": 1,
      "retweet_count": 1,
      "reply_count": 0,
      "sentiment": "negative",
      "sentiment_score": -0.06609466671943665
    },
    {
      "id": "1902044086519124339",
      "text": "Salman Khan likely to attend IPL 2025 opening ceremony.(HT). https://t.co/ArZEcPjJsp",
      "cleaned_text": "salman khan likely to attend ipl 2025 opening ceremony ht ",
      "favorite_count": 13,
      "retweet_count": 5,
      "reply_count": 0,
      "sentiment": "positive",
      "sentiment_score": 0.139417827129364
    },
    {
      "id": "1902043923486536020",
      "text": "This IPL Is Going To Full Of Entertainment!🍿🤩🥳 https://t.co/KWCNsZgfzt",
      "cleaned_text": "this ipl is going to full of entertainment ",
      "favorite_count": 380,
      "retweet_count": 14,
      "reply_count": 16,
      "sentiment": "positive",
      "sentiment_score": 0.30629855394363403
    },
    {
      "id": "1902043272937451973",
      "text": "आईपीएल आ रहा है\nसभी RCB पंखों बुकमार्क कर लो\nबार बार ट्रोल न कर पाऊंगा तुम्हें और तुम्हारी टीम को\n#RCB #IPL https://t.co/GIJd0kJmNq",
      "cleaned_text": "आईप एल आ रह ह सभ rcb प ख ब कम र क कर ल ब र ब र ट र ल न कर प ऊ ग त म ह और त म ह र ट म क ",
      "favorite_count": 4,
      "retweet_count": 2,
      "reply_count": 0,
      "sentiment": "neutral",
      "sentiment_score": 0.026860922574996948
    },
    {
      "id": "1902043140066095589",
      "text": ".\n                     🕯     🕯\n           🕯                        🕯\n                       IK\n       🕯          1000+         🕯\n                       IPL runs \n           🕯                        🕯\n                    🕯      🕯\n\n#IshanKishan\n#IPL2025\n#PlayWithFire",
      "cleaned_text": " ik 1000 ipl runs ",
      "favorite_count": 6,
      "retweet_count": 2,
      "reply_count": 0,
      "sentiment": "negative",
      "sentiment_score": -0.10133806616067886
    },
    {
      "id": "1902043085351350357",
      "text": "KL Rahul is ready to bat at any position for Delhi Capitals in IPL 2025, whether as an opener or in the middle order. Because for KL, the team comes first always, He is a complete team man. 🫡\n\nThe selfless KL Rahul for you! 💙\n\n#KLRahul #DelhiCapitals #DC #IPL2025 #TATAIPL2025 https://t.co/TFHXFMsFFc",
      "cleaned_text": "kl rahul is ready to bat at any position for delhi capitals in ipl 2025 whether as an opener or in the middle order because for kl the team comes first always he is a complete team man the selfless kl rahul for you ",
      "favorite_count": 2,
      "retweet_count": 1,
      "reply_count": 0,
      "sentiment": "positive",
      "sentiment_score": 0.3956596851348877
    },
    {
      "id": "1902042582823149765",
      "text": "🚨🤩 Salman Khan and Shah Rukh Khan likely to attend IPL 2025 opening ceremony.\n\n- @/htTweets https://t.co/L3WI6sgUGU",
      "cleaned_text": " salman khan and shah rukh khan likely to attend ipl 2025 opening ceremony httweets ",
      "favorite_count": 33,
      "retweet_count": 2,
      "reply_count": 1,
      "sentiment": "positive",
      "sentiment_score": 0.10859308391809464
    },
    {
      "id": "1902042575693082686",
      "text": "MEGASTARS #SalmanKhan and #SRK to attend IPL OPENING CEREMONY🔥 https://t.co/WA36GrZtLv",
      "cleaned_text": "megastars and to attend ipl opening ceremony ",
      "favorite_count": 130,
      "retweet_count": 10,
      "reply_count": 6,
      "sentiment": "positive",
      "sentiment_score": 0.25520044565200806
    },
    {
      "id": "1902042513936130555",
      "text": "Twitter kyu itna cringe ho raha hai\n\nKoi girl space bana raha hai koi ipl ka space bana raha hai koi fandoms wala bana raha hai chill space kaha milega😔",
      "cleaned_text": "twitter kyu itna cringe ho raha hai koi girl space bana raha hai koi ipl ka space bana raha hai koi fandoms wala bana raha hai chill space kaha milega ",
      "favorite_count": 2,
      "retweet_count": 1,
      "reply_count": 1,
      "sentiment": "negative",
      "sentiment_score": -0.2446233630180359
    },
    {
      "id": "1902042491186233456",
      "text": "Hukum song to ipl franchises https://t.co/HdekMxl1Ev",
      "cleaned_text": "hukum song to ipl franchises ",
      "favorite_count": 3,
      "retweet_count": 1,
      "reply_count": 1,
      "sentiment": "neutral",
      "sentiment_score": -0.02081616222858429
    },
    {
      "id": "1902042325100195965",
      "text": "@CrazyBoyXSystum Mai btata hu isko laat marke bhaga denge sab 4 log jante bs ipl me dekhte isko sab bkki time laat mare rhte h sab🤡😂",
      "cleaned_text": " mai btata hu isko laat marke bhaga denge sab 4 log jante bs ipl me dekhte isko sab bkki time laat mare rhte h sab ",
      "favorite_count": 6,
      "retweet_count": 1,
      "reply_count": 0,
      "sentiment": "negative",
      "sentiment_score": -0.1110265851020813
    },
    {
      "id": "1902042323267068043",
      "text": "After Jasprit Bumrah, Another India Player Who Got Injured During BGT To Miss Start Of IPL 2025 - Report\n\nhttps://t.co/lspq5yankh",
      "cleaned_text": "after jasprit bumrah another india player who got injured during bgt to miss start of ipl 2025 report ",
      "favorite_count": 1,
      "retweet_count": 1,
      "reply_count": 0,
      "sentiment": "negative",
      "sentiment_score": -0.8111734390258789
    },
    {
      "id": "1902042265305899431",
      "text": "Probably, MEGASTAR SALMAN KHAN can make his presence in the opening ceremony of IPL\n\n#Sikandar #SalmanKhan",
      "cleaned_text": "probably megastar salman khan can make his presence in the opening ceremony of ipl ",
      "favorite_count": 32,
      "retweet_count": 14,
      "reply_count": 1,
      "sentiment": "positive",
      "sentiment_score": 0.37350085377693176
    },
    {
      "id": "1902042231030075762",
      "text": "@Manas263 80% roshit fc believes he is top 5 ipl player 😭😭\nMai toh imagine nahi kr skta if they repped someone like Ab or Kohli kya haal krte ye log",
      "cleaned_text": " 80 roshit fc believes he is top 5 ipl player mai toh imagine nahi kr skta if they repped someone like ab or kohli kya haal krte ye log",
      "favorite_count": 6,
      "retweet_count": 1,
      "reply_count": 4,
      "sentiment": "negative",
      "sentiment_score": -0.19162973761558533
    },
    {
      "id": "1902042194162467262",
      "text": "Which is your Most and Least Favourite Jersey of IPL 2025 ? \n\nMy Most Fav Is KKR And Least Fav Is DC https://t.co/ZFuF1rHSAi",
      "cleaned_text": "which is your most and least favourite jersey of ipl 2025 my most fav is kkr and least fav is dc ",
      "favorite_count": 20,
      "retweet_count": 3,
      "reply_count": 13,
      "sentiment": "positive",
      "sentiment_score": 0.10066226124763489
    },
    {
      "id": "1902041943301067087",
      "text": "🚨| American pop band OneRepublic has also been approached to deliver a performance in IPL 2025 Opening Ceremony. \n\n~ Hindustan Times https://t.co/lhufc2gRPF",
      "cleaned_text": " american pop band onerepublic has also been approached to deliver a performance in ipl 2025 opening ceremony hindustan times ",
      "favorite_count": 24,
      "retweet_count": 5,
      "reply_count": 0,
      "sentiment": "positive",
      "sentiment_score": 0.2191210389137268
    },
    {
      "id": "1902041828096127019",
      "text": "• THE DISTANCE TEAMS WILL TRAVEL IN THIS IPL 2025:✈️\n\nRCB - 17,084 Km.\nCSK - 16,184 Km.\nPBKS - 14,341 Km.\nKKR - 13,537 Km.\nRR - 12,730 Km.\nMI - 12,702 Km.\nGT - 10,405 Km.\nLSG - 9,747 Km.\nDC - 9,270 Km.\nSRH - 8,536 Km.\n\n• RCB team travelling the most distance in #IPL2025.\n\n#RCB https://t.co/n2AXCP9ODr",
      "cleaned_text": " the distance teams will travel in this ipl 2025 rcb 17 084 km csk 16 184 km pbks 14 341 km kkr 13 537 km rr 12 730 km mi 12 702 km gt 10 405 km lsg 9 747 km dc 9 270 km srh 8 536 km rcb team travelling the most distance in ",
      "favorite_count": 1,
      "retweet_count": 1,
      "reply_count": 0,
      "sentiment": "negative",
      "sentiment_score": -0.05550116300582886
    },
    {
      "id": "1902041725079883909",
      "text": "@mufaddal_vohra Crowd favourite Heinrich KLAASEN has landed in Hyderabad for IPL 2025🧡🍊\n\nhttps://t.co/SuPzxeSrI0",
      "cleaned_text": " crowd favourite heinrich klaasen has landed in hyderabad for ipl 2025 ",
      "favorite_count": 1,
      "retweet_count": 2,
      "reply_count": 0,
      "sentiment": "positive",
      "sentiment_score": 0.23089560866355896
    },
    {
      "id": "1902041722982654327",
      "text": "My prediction \nTop 4 teams ipl 2025\n1. SRH \n2. MI\n3. CSK \n4. RR",
      "cleaned_text": "my prediction top 4 teams ipl 2025 1 srh 2 mi 3 csk 4 rr",
      "favorite_count": 10,
      "retweet_count": 2,
      "reply_count": 5,
      "sentiment": "negative",
      "sentiment_score": -0.050743669271469116
    },
    {
      "id": "1902041631622341009",
      "text": "Mil gaya Marsh ka replacement 👇 https://t.co/SpmOPMEUNP",
      "cleaned_text": "mil gaya marsh ka replacement ",
      "favorite_count": 550,
      "retweet_count": 50,
      "reply_count": 52,
      "sentiment": "neutral",
      "sentiment_score": -0.0316426157951355
    },
    {
      "id": "1902041345923203388",
      "text": "The 𝐉𝐨𝐲 of Sport! 🏏✨\n\n#WhistlePodu #Yellove 🦁💛 https://t.co/TTg9RDUu0I",
      "cleaned_text": "the 𝐉𝐨𝐲 of sport ",
      "favorite_count": 2464,
      "retweet_count": 164,
      "reply_count": 25,
      "sentiment": "positive",
      "sentiment_score": 0.8733460903167725
    },
    {
      "id": "1902041262221619313",
      "text": "All time favourite ipl pic of। rohit sharma 🔥 \n\n#RohitSharma𓃵 https://t.co/0tN3dsZirZ",
      "cleaned_text": "all time favourite ipl pic of rohit sharma ",
      "favorite_count": 4,
      "retweet_count": 2,
      "reply_count": 0,
      "sentiment": "positive",
      "sentiment_score": 0.29640522599220276
    },
    {
      "id": "1902041222468006299",
      "text": "@England593 This is getting cringe now .\nKohli the test batsman is infinite tiers above ro suar  the ipl bat",
      "cleaned_text": " this is getting cringe now kohli the test batsman is infinite tiers above ro suar the ipl bat",
      "favorite_count": 12,
      "retweet_count": 1,
      "reply_count": 1,
      "sentiment": "negative",
      "sentiment_score": -0.8062058091163635
    },
    {
      "id": "1902041182475317564",
      "text": "Meanwhile IPL chairman: \n\n https://t.co/vLptZ22Z0g",
      "cleaned_text": "meanwhile ipl chairman ",
      "favorite_count": 34,
      "retweet_count": 16,
      "reply_count": 0,
      "sentiment": "negative",
      "sentiment_score": -0.1715192049741745
    },
    {
      "id": "1902041033141293065",
      "text": "The best one among all ipl captains.🔥🔥 AURA ♾️♾️",
      "cleaned_text": "the best one among all ipl captains aura ",
      "favorite_count": 32,
      "retweet_count": 4,
      "reply_count": 0,
      "sentiment": "positive",
      "sentiment_score": 0.6993518471717834
    },
    {
      "id": "1902040986303525090",
      "text": "@CricCrazyJohns Most dengerous opener in IPL \n\nIshan kishan \nAbhishek Sharma \n\nhttps://t.co/EIQZ8sZSsP",
      "cleaned_text": " most dengerous opener in ipl ishan kishan abhishek sharma ",
      "favorite_count": 1,
      "retweet_count": 1,
      "reply_count": 0,
      "sentiment": "negative",
      "sentiment_score": -0.28411757946014404
    },
    {
      "id": "1902040899925758079",
      "text": "Suresh Raina is widely known as \"Mr. IPL\" for his consistent performances in the Indian Premier League. He's the fifth-highest run-scorer in IPL history with 5,528 runs in 205 matches, shining especially with Chennai Super Kings. Even after retiring in 2021, his nickname sticks in 2025, showing his lasting impact!",
      "cleaned_text": "suresh raina is widely known as mr ipl for his consistent performances in the indian premier league he s the fifth highest run scorer in ipl history with 5 528 runs in 205 matches shining especially with chennai super kings even after retiring in 2021 his nickname sticks in 2025 showing his lasting impact ",
      "favorite_count": 1,
      "retweet_count": 1,
      "reply_count": 0,
      "sentiment": "positive",
      "sentiment_score": 0.41969525814056396
    },
    {
      "id": "1902040781055254783",
      "text": "Yes bro ekkuva sepu adute maa india win avtundi 😗💙\nAnyday ICT&gt;IPL https://t.co/x42WyJHqNI",
      "cleaned_text": "yes bro ekkuva sepu adute maa india win avtundi anyday ict gt ipl ",
      "favorite_count": 3,
      "retweet_count": 1,
      "reply_count": 0,
      "sentiment": "neutral",
      "sentiment_score": -0.024581432342529297
    },
    {
      "id": "1902040647114375327",
      "text": "🚨| Other Names on the Guest List are Triptii Dimri, Ananya Panday and Madhuri Dixit for IPL 2025 Opening Ceremony. \n\n~ Hindustan Times https://t.co/Ei34x044rE",
      "cleaned_text": " other names on the guest list are triptii dimri ananya panday and madhuri dixit for ipl 2025 opening ceremony hindustan times ",
      "favorite_count": 45,
      "retweet_count": 6,
      "reply_count": 2,
      "sentiment": "neutral",
      "sentiment_score": 0.016175657510757446
    },
    {
      "id": "1902040450388856975",
      "text": "This is Lit 🔥\n\nSomething different from others \n\n#IPL #RR #TATAIPL",
      "cleaned_text": "this is lit something different from others ",
      "favorite_count": 4,
      "retweet_count": 1,
      "reply_count": 0,
      "sentiment": "negative",
      "sentiment_score": -0.23692205548286438
    },
    {
      "id": "1902040449025486982",
      "text": "THE DISTANCE TEAMS WILL TRAVEL IN THIS IPL 2025: ✈️ \n\nRCB - 17,084 Km.\nCSK - 16,184 Km.\nPBKS - 14,341 Km.\nKKR - 13,537 Km.\nRR - 12,730 Km.\nMI - 12,702 Km.\nGT - 10,405 Km.\nLSG - 9,747 Km.\nDC - 9,270 Km.\nSRH - 8,536 Km. https://t.co/fpcYMdZg5c",
      "cleaned_text": "the distance teams will travel in this ipl 2025 rcb 17 084 km csk 16 184 km pbks 14 341 km kkr 13 537 km rr 12 730 km mi 12 702 km gt 10 405 km lsg 9 747 km dc 9 270 km srh 8 536 km ",
      "favorite_count": 637,
      "retweet_count": 67,
      "reply_count": 20,
      "sentiment": "neutral",
      "sentiment_score": -0.040183380246162415
    },
    {
      "id": "1902040369120104885",
      "text": "#SalmanKhan Will Attend #Ipl Opening Ceremony to Promote #Sikandar 🔥\nHopefully for the Trailer Launch 🤞🏻\n@BeingSalmanKhan https://t.co/mUtjhqzJ3U",
      "cleaned_text": " will attend opening ceremony to promote hopefully for the trailer launch ",
      "favorite_count": 62,
      "retweet_count": 29,
      "reply_count": 0,
      "sentiment": "positive",
      "sentiment_score": 0.28254106640815735
    },
    {
      "id": "1902040353915728385",
      "text": "King @iamsrk will attend IPL 2025 opening ceremony. https://t.co/85f2R5ngKf",
      "cleaned_text": "king will attend ipl 2025 opening ceremony ",
      "favorite_count": 29,
      "retweet_count": 10,
      "reply_count": 1,
      "sentiment": "positive",
      "sentiment_score": 0.22803804278373718
    },
    {
      "id": "1902040219962253487",
      "text": "#HardikPandya, #ShreyasIyer Eye History In IPL 2025 With Title Win, Eye Chance To Become First Player In The World To...\n#IPL2025\nhttps://t.co/LwXQCFgT2A",
      "cleaned_text": " eye history in ipl 2025 with title win eye chance to become first player in the world to ",
      "favorite_count": 6,
      "retweet_count": 1,
      "reply_count": 0,
      "sentiment": "positive",
      "sentiment_score": 0.4419586658477783
    },
    {
      "id": "1902039834279211445",
      "text": "🚨 RCB TEAM WILL BE TOUCHES HIGHEST DURATION DURING IPL 🚨.\n\n- RCB is likely to travel 17,084 Km in all Matches. https://t.co/NIUs7SGSs7",
      "cleaned_text": " rcb team will be touches highest duration during ipl rcb is likely to travel 17 084 km in all matches ",
      "favorite_count": 1,
      "retweet_count": 1,
      "reply_count": 1,
      "sentiment": "positive",
      "sentiment_score": 0.07696150243282318
    },
    {
      "id": "1902039315359928411",
      "text": "8 yrs avuthundhi correct ipl aadi still ee record lo ayina untadu adi puli @ImRo45 set chesina standards 🔥🔥🔥🔥🔥\nROHIT GURUNATH SHARMA 🐐\na talented batsmen who never played for his potential https://t.co/4nmWzZkv1x",
      "cleaned_text": "8 yrs avuthundhi correct ipl aadi still ee record lo ayina untadu adi puli set chesina standards rohit gurunath sharma a talented batsmen who never played for his potential ",
      "favorite_count": 8,
      "retweet_count": 4,
      "reply_count": 1,
      "sentiment": "neutral",
      "sentiment_score": 0.01360437273979187
    },
    {
      "id": "1902039217821380657",
      "text": "🚨 RCB WILL TRAVEL THE MAXIMUM DISTANCE IN THIS IPL 2025 🚨\n\n- RCB Will Travel 17,084 KM during this IPL 2025..!!!! https://t.co/6JeLMp7pmn",
      "cleaned_text": " rcb will travel the maximum distance in this ipl 2025 rcb will travel 17 084 km during this ipl 2025 ",
      "favorite_count": 592,
      "retweet_count": 50,
      "reply_count": 5,
      "sentiment": "positive",
      "sentiment_score": 0.13310599327087402
    },
    {
      "id": "1902039084148912348",
      "text": "🚨| Vicky Kaushal &amp; Katrina Kaif are also on the Guest List of IPL Opening Ceremony. \n\n~ Hindustan Times https://t.co/vvWVRJDQ0Q",
      "cleaned_text": " vicky kaushal amp katrina kaif are also on the guest list of ipl opening ceremony hindustan times ",
      "favorite_count": 28,
      "retweet_count": 5,
      "reply_count": 1,
      "sentiment": "positive",
      "sentiment_score": 0.08749531209468842
    },
    {
      "id": "1902038836970189089",
      "text": "Most Wickets in IPL against a Team \n\n35 - Umesh v PBKS\n34 - Narine v PBKS\n33 - Bravo v MI\n33 - Mohit v MI\n32 - Chahal v PBKS\n32 - Bhuvi v KKR\n31 - Malinga v CSK\n31 - Mishra v RR\n29 - Bumrah v KKR\n29 - Chahal v KKR\n29 - Chahal v MI\n29 - Bhuvi v PBKS",
      "cleaned_text": "most wickets in ipl against a team 35 umesh v pbks 34 narine v pbks 33 bravo v mi 33 mohit v mi 32 chahal v pbks 32 bhuvi v kkr 31 malinga v csk 31 mishra v rr 29 bumrah v kkr 29 chahal v kkr 29 chahal v mi 29 bhuvi v pbks",
      "favorite_count": 89,
      "retweet_count": 6,
      "reply_count": 10,
      "sentiment": "negative",
      "sentiment_score": -0.09236070513725281
    },
    {
      "id": "1902038485868945733",
      "text": "Yo @Vikas_Spidey_17! SRH has been RCB's nightmare for real 💥🤙. They’ve kicked RCB out of the IPL tournament 4 times in playoffs:  \n- 2009 Final (DC beat RCB)  \n- 2016 Final (SRH smoked RCB)  \n- 2017 Eliminator (SRH sent RCB packing)  \n- 2020 Eliminator (SRH crushed RCB’s hopes)  \nThat’s 4 direct eliminations, bro! SRH owns that playoff vibe against RCB 🔥",
      "cleaned_text": "yo srh has been rcb s nightmare for real they ve kicked rcb out of the ipl tournament 4 times in playoffs 2009 final dc beat rcb 2016 final srh smoked rcb 2017 eliminator srh sent rcb packing 2020 eliminator srh crushed rcb s hopes that s 4 direct eliminations bro srh owns that playoff vibe against rcb ",
      "favorite_count": 2,
      "retweet_count": 1,
      "reply_count": 1,
      "sentiment": "negative",
      "sentiment_score": -0.7417371273040771
    },
    {
      "id": "1902038396681515087",
      "text": "🥹🥹🥹 https://t.co/vQZaneQXWj",
      "cleaned_text": " ",
      "favorite_count": 35,
      "retweet_count": 3,
      "reply_count": 3,
      "sentiment": "neutral",
      "sentiment_score": -0.03498560190200806
    },
    {
      "id": "1902038270713999650",
      "text": "Megastar #SalmanKhan likely to attend IPL 2025 opening ceremony. #Ipl2025 #Sikandar https://t.co/g49CRMJ55W",
      "cleaned_text": "megastar likely to attend ipl 2025 opening ceremony ",
      "favorite_count": 3,
      "retweet_count": 2,
      "reply_count": 0,
      "sentiment": "positive",
      "sentiment_score": 0.30828383564949036
    },
    {
      "id": "1902038246823227437",
      "text": "Reports say SRK &amp; Salman might attend IPL 2025 opening ceremony. \nHonestly… does it even matter? Isn’t IPL already bigger than Bollywood? The real stars are on the pitch.\nWhat do you think — Do celebs add value or is cricket enough?",
      "cleaned_text": "reports say srk amp salman might attend ipl 2025 opening ceremony honestly does it even matter isn t ipl already bigger than bollywood the real stars are on the pitch what do you think do celebs add value or is cricket enough ",
      "favorite_count": 37,
      "retweet_count": 28,
      "reply_count": 28,
      "sentiment": "negative",
      "sentiment_score": -0.15795326232910156
    },
    {
      "id": "1902038191395553578",
      "text": "@Kelly131339867 I support KKR IPL me \nAap log kis team ko support karte hai \n\nAYANAM CHUMVEER",
      "cleaned_text": " i support kkr ipl me aap log kis team ko support karte hai ayanam chumveer",
      "favorite_count": 9,
      "retweet_count": 18,
      "reply_count": 0,
      "sentiment": "neutral",
      "sentiment_score": 0.010590404272079468
    },
    {
      "id": "1902038104980255000",
      "text": "A BLINDER BY SHRIJITH 🤯\n\n- A youngster to watch out from Karnataka in IPL 2025. https://t.co/rHadYSy1SG",
      "cleaned_text": "a blinder by shrijith a youngster to watch out from karnataka in ipl 2025 ",
      "favorite_count": 1068,
      "retweet_count": 36,
      "reply_count": 41,
      "sentiment": "neutral",
      "sentiment_score": -0.029932081699371338
    },
    {
      "id": "1902037917956223327",
      "text": "@Kelly131339867 IPL me Fev team kaunsa hai \nAYANAM CHUMVEER",
      "cleaned_text": " ipl me fev team kaunsa hai ayanam chumveer",
      "favorite_count": 9,
      "retweet_count": 13,
      "reply_count": 0,
      "sentiment": "negative",
      "sentiment_score": -0.08059677481651306
    },
    {
      "id": "1902037908451889368",
      "text": "@pushkar_g_singh @PaulAtk52540619 @CullivanPeter @CricketopiaCom @realomerlatif @alawyerwrites @kediwins @DaveRob13699163 @_AQuietLife_ Then #Imran &amp; #Sarfraz Plus #Lillie &amp; #Thommo_ _Kalicharan and Greenidge Further I would have love to Watch #Ramnath_Parkar in the #IPL__ to @VAAChandran @Kediwins  @PrasunNagar  @PaulAtk52540619",
      "cleaned_text": " then amp plus amp _kalicharan and greenidge further i would have love to watch in the to ",
      "favorite_count": 1,
      "retweet_count": 1,
      "reply_count": 0,
      "sentiment": "positive",
      "sentiment_score": 0.29129064083099365
    },
    {
      "id": "1902037761131209125",
      "text": "@Kelly131339867 IPL kaun kaun dekhta hai\nAYANAM CHUMVEER",
      "cleaned_text": " ipl kaun kaun dekhta hai ayanam chumveer",
      "favorite_count": 5,
      "retweet_count": 8,
      "reply_count": 0,
      "sentiment": "negative",
      "sentiment_score": -0.09161487221717834
    },
    {
      "id": "1902037626720518147",
      "text": "#Cricket24 #IPL2025 #PBKS #KapCha42\n\n📢Here you go @PunjabKingsIPL @IPL\n\nKit Created for Cricket 24🎮on demand🤞\n------ \nTo Download 📩Search 🔎\n👉Community Creator - \"KapCha42\"\n------ \nLike ----> ❤\n------\n✅Follow & Join for Quick Updates\n📍Discord : https://t.co/LHJb3vdgKC\n& \nX (Twitter) Cricket24 PlayFace Community :\nhttps://t.co/5LaxLTaYSL",
      "cleaned_text": " here you go kit created for cricket 24 on demand to download search community creator kapcha42 like follow join for quick updates discord x twitter cricket24 playface community ",
      "favorite_count": 7,
      "retweet_count": 2,
      "reply_count": 1,
      "sentiment": "positive",
      "sentiment_score": 0.18157698214054108
    },
    {
      "id": "1902037546869363050",
      "text": "India Pacer Backed To Shine In IPL After Champions Trophy 2025 Snub: \"Wasn't There...\"\n\nhttps://t.co/lUlEaJjo4X https://t.co/unEMFWEdIs",
      "cleaned_text": "india pacer backed to shine in ipl after champions trophy 2025 snub wasn t there ",
      "favorite_count": 7,
      "retweet_count": 1,
      "reply_count": 0,
      "sentiment": "negative",
      "sentiment_score": -0.2863592505455017
    },
    {
      "id": "1902037535637025276",
      "text": "Megastar #SalmanKhan likely to attend IPL 2025 opening ceremony. (HT). https://t.co/0XQkgTXp9Y",
      "cleaned_text": "megastar likely to attend ipl 2025 opening ceremony ht ",
      "favorite_count": 32,
      "retweet_count": 9,
      "reply_count": 0,
      "sentiment": "positive",
      "sentiment_score": 0.24901805818080902
    },
    {
      "id": "1902037365734203434",
      "text": "🚨| Shah Rukh Khan and Salman Khan are likely to attend IPL 2025 Opening Ceremony. \n\n~ Hindustan Times https://t.co/oCKR48w7T9",
      "cleaned_text": " shah rukh khan and salman khan are likely to attend ipl 2025 opening ceremony hindustan times ",
      "favorite_count": 63,
      "retweet_count": 9,
      "reply_count": 0,
      "sentiment": "positive",
      "sentiment_score": 0.12461124360561371
    },
    {
      "id": "1902037217448771874",
      "text": "CT FINALISTS WERE GIVEN AT THE STARTING OF LEAGUE.\nJoin my Telegram to get IPL 2025 Winners and Match Predictions 👇\n\nhttps://t.co/ydEzfWn65A\nhttps://t.co/ydEzfWn65A\n\n#CricketTwitter #ipl2025schedule #IPL #IPLUpdate #RCBUnbox #ViratKohli𓃵 #MSDhoni𓃵 #Cricket https://t.co/fJ4iPM8hEP",
      "cleaned_text": "ct finalists were given at the starting of league join my telegram to get ipl 2025 winners and match predictions ",
      "favorite_count": 17,
      "retweet_count": 8,
      "reply_count": 7,
      "sentiment": "neutral",
      "sentiment_score": 0.03480815887451172
    },
    {
      "id": "1902037074704060708",
      "text": "Ms Dhoni is the only Indian player to play the World Cup for New Zealand and IPL for Mumbai Indians in the same year 2019. https://t.co/mMzpuzHhm8",
      "cleaned_text": "ms dhoni is the only indian player to play the world cup for new zealand and ipl for mumbai indians in the same year 2019 ",
      "favorite_count": 10,
      "retweet_count": 1,
      "reply_count": 1,
      "sentiment": "neutral",
      "sentiment_score": -0.027023613452911377
    },
    {
      "id": "1902036830922625326",
      "text": "Who misses these IPL Anthems?😫 https://t.co/u2QHi0mu3C",
      "cleaned_text": "who misses these ipl anthems ",
      "favorite_count": 41,
      "retweet_count": 3,
      "reply_count": 5,
      "sentiment": "negative",
      "sentiment_score": -0.7787481546401978
    },
    {
      "id": "1902036726476087770",
      "text": "@Badpatch18 Reason why ICC trophies, Asia Cup &amp; IPL look small",
      "cleaned_text": " reason why icc trophies asia cup amp ipl look small",
      "favorite_count": 84,
      "retweet_count": 1,
      "reply_count": 0,
      "sentiment": "negative",
      "sentiment_score": -0.8193973898887634
    },
    {
      "id": "1902036479129649630",
      "text": "#Jaipur RCA एडहॉक कमेटी की बैठक हुई आयोजित\n\nएडहॉक कमेटी कन्वीनर जयदीप  बिहानी  की अध्यक्षता में आयोजित हुई बैठक, बैठक के बाद बोले जयदीप  बिहानी - IPL आयोजन को लेकर नहीं है कोई टकराव, पार्टी का सिपाही कंट्रोवर्सी नहीं करेगा, कोई मतभेद होंगे तो बंद कमरे में निपटा लिए जाएंगे, केंद्र और राज्य दोनों ही जगह भारतीय जनता पार्टी की सरकार फिलहाल तीन महीने तक एडहॉक कमेटी का कार्यकाल बचा हुआ है\n\n@sachin_journo @IPL #RajasthanNews #RajasthanWithZee #LatestNews",
      "cleaned_text": " rca एडह क कम ट क ब ठक ह ई आय ज त एडह क कम ट कन व नर जयद प ब ह न क अध यक षत म आय ज त ह ई ब ठक ब ठक क ब द ब ल जयद प ब ह न ipl आय जन क ल कर नह ह क ई टकर व प र ट क स प ह क ट र वर स नह कर ग क ई मतभ द ह ग त ब द कमर म न पट ल ए ज ए ग क द र और र ज य द न ह जगह भ रत य जनत प र ट क सरक र फ लह ल त न मह न तक एडह क कम ट क क र यक ल बच ह आ ह ",
      "favorite_count": 2,
      "retweet_count": 1,
      "reply_count": 0,
      "sentiment": "negative",
      "sentiment_score": -0.07279998064041138
    },
    {
      "id": "1902036341338337303",
      "text": "@Shebas_10dulkar Rohit scored 8 six in IPL final till now",
      "cleaned_text": " rohit scored 8 six in ipl final till now",
      "favorite_count": 11,
      "retweet_count": 1,
      "reply_count": 0,
      "sentiment": "neutral",
      "sentiment_score": 0.014387726783752441
    }
  ]
}